termaths/__init__.py
termaths/complexe.py
termaths/matrice.py
termaths-0.0.4.dist-info/LICENSE
termaths-0.0.4.dist-info/METADATA
termaths-0.0.4.dist-info/WHEEL
termaths-0.0.4.dist-info/top_level.txt
termaths-0.0.4.dist-info/RECORD
