Metadata-Version: 2.1
Name: termaths
Version: 0.0.4
Summary: Un module de maths pour des élèves de terminales en spécialité maths ou en maths expertes.
Home-page: https://github.com/benoitrx2/termaths
Author: Benoit Roux
Author-email: b.roux3850@gmail.com
License: UNKNOWN
Project-URL: Bug Tracker, https://github.com/benoitrx2/termaths/issues
Platform: UNKNOWN
Classifier: Programming Language :: Python :: 3
Classifier: License :: OSI Approved :: MIT License
Classifier: Operating System :: OS Independent
Requires-Python: >=3.6
License-File: LICENSE
